concap/__init__.py
concap/py.typed
concap-0.2.1.dist-info/LICENSE
concap-0.2.1.dist-info/METADATA
concap-0.2.1.dist-info/WHEEL
concap-0.2.1.dist-info/top_level.txt
concap-0.2.1.dist-info/RECORD
