Metadata-Version: 2.1
Name: concap
Version: 0.2.1
Summary: An interactive console implement.
Home-page: https://github.com/NCBM/concap
Author: HivertMoZara
Author-email: worldmozara@163.com
License: UNKNOWN
Platform: UNKNOWN
Classifier: Operating System :: OS Independent
Classifier: Programming Language :: Python :: 3
Classifier: Development Status :: 2 - Pre-Alpha
Classifier: License :: OSI Approved :: MIT License
Requires-Python: >=3.7.0
License-File: LICENSE
